{"i":{"trje9VYQj":{"id":"trje9VYQj","type":"slide","setup":{"bord":{"size":0,"rad":0},"bg":{"selectedKey":"image","fill":{"opac":1,"rgb":"var(--TC3)"},"img":{"filt":{"opac":100,"gray":0,"blur":0,"tint":{"rgb":"var(--TC3)","opac":0.5,"blendMode":"multiply"}},"pos":{"type":"crop","fit":{"bg":{"color":{"rgb":"#FFF","opac":100}},"vali":"center","hali":"center"},"crop":{"poi":{"x":540,"y":1534.5}}},"measures":{"size":{"width":1080,"height":1920}}}},"transparentBg":{"selectedKey":false}}},"u7S9GG7WXT":{"id":"u7S9GG7WXT","type":"interactive","subtype":"interactiveRichText","setup":{"frmeTp":{"selectedKey":"bottomLine"},"bg":{"selectedKey":"fill","fill":{"opac":1,"rgb":"var(--TC14)"}},"txt":{"val":{"ops":[{"insert":"Estructura clara para un proyecto de investigación aplicada","attributes":{"color":"#19547a","bold":true,"lang":"ES-MX","background":"rgba(0, 0, 0, 0)"}},{"insert":"\n","attributes":{"size":"largeTitle","align":"center"}}]},"rType":"richtext"},"vali":"middle","hali":"","frmeColo":{"color":{"opac":1,"rgb":"#19547a"}},"paddV1":44}},"jX3vf6kSu5":{"id":"jX3vf6kSu5","type":"interactive","subtype":"interactiveRichText","setup":{"frmeTp":{"selectedKey":"noneFrame"},"bg":{"selectedKey":"fill","fill":{"opac":1,"rgb":"#19547a"}},"txt":{"val":{"ops":[{"insert":"5. Resultados y Conclusiones","attributes":{"bold":true,"lang":"ES-ES","color":"var(--TC14)"}},{"insert":"\n\n","attributes":{"align":"justify"}},{"attributes":{"lang":"ES-ES","color":"var(--TC14)"},"insert":"Presenta los resultados obtenidos y las conclusiones que se derivan de la investigación."},{"attributes":{"color":"var(--TC14)"},"insert":" "},{"insert":"\n","attributes":{"align":"justify"}}]},"rType":"richtext"},"paddV1":36,"hali":"","vali":"middle"}},"nhhDDWOUnI":{"id":"nhhDDWOUnI","type":"interactive","subtype":"interactiveCoverFlow","setup":{"style":{"selectedKey":"textOverlapping"},"title":{"rType":"text","tag":"p"},"animation":{"selectedKey":"horizontal"},"imgs":{"i":{"RgjyAS79i":{"type":"image","id":"RgjyAS79i","txtBg":{"fill":{"opac":1,"rgb":"var(--TC14)"}},"img":{"filt":{"opac":100,"gray":0,"blur":0,"tint":{"rgb":"#FFF","opac":0}},"pos":{"type":"crop","fit":{"bg":{"color":{"rgb":"#FFF","opac":100},"gradient":{"angle":0,"opac":0.5,"stops":[{"color":"#000000","pos":0},{"color":"#000000","pos":100}]}},"vali":"center","hali":"center"},"crop":{"bg":{"color":{"rgb":"#FFF","opac":0},"gradient":{"angle":0,"opac":0.5,"stops":[{"color":"#000000","pos":0},{"color":"#000000","pos":100}]}},"poi":{"orig":{"x":50,"y":50},"cust":{"x":50,"y":50}}},"mask":{"shape":1,"bg":{"color":{"rgb":"#FFF","opac":0},"gradient":{"angle":0,"opac":0.5,"stops":[{"color":"#000000","pos":0},{"color":"#000000","pos":100}]}}}}},"desc":{"val":{"ops":[{"insert":"a. Presentación de resultados","attributes":{"bold":true,"lang":"ES-ES","color":"var(--TC13)"}},{"insert":"\n\n","attributes":{"align":"center","size":"normal"}},{"insert":"Muestra los datos recopilados de manera clara, utilizando tablas, gráficos u otros medios.","attributes":{"lang":"ES-ES","color":"var(--TC13)"}},{"insert":"\n","attributes":{"align":"justify","size":"normal"}}]},"rType":"richtext","paddV1":80,"hali":""}},"Ur2T_-mJj":{"type":"image","id":"Ur2T_-mJj","txtBg":{"fill":{"opac":1,"rgb":"var(--TC14)"}},"img":{"filt":{"opac":100,"gray":0,"blur":0,"tint":{"rgb":"#FFF","opac":0}},"pos":{"type":"crop","fit":{"bg":{"color":{"rgb":"#FFF","opac":100},"gradient":{"angle":0,"opac":0.5,"stops":[{"color":"#000000","pos":0},{"color":"#000000","pos":100}]}},"vali":"center","hali":"center"},"crop":{"bg":{"color":{"rgb":"#FFF","opac":0},"gradient":{"angle":0,"opac":0.5,"stops":[{"color":"#000000","pos":0},{"color":"#000000","pos":100}]}},"poi":{"orig":{"x":50,"y":50},"cust":{"x":50,"y":50}}},"mask":{"shape":1,"bg":{"color":{"rgb":"#FFF","opac":0},"gradient":{"angle":0,"opac":0.5,"stops":[{"color":"#000000","pos":0},{"color":"#000000","pos":100}]}}}}},"desc":{"val":{"ops":[{"insert":"b. Interpretación y análisis de datos","attributes":{"bold":true,"lang":"ES-ES","color":"var(--TC13)"}},{"insert":"\n\n","attributes":{"align":"center","size":"normal"}},{"insert":"Analiza los resultados y proporciona interpretaciones basadas en la evidencia recopilada.","attributes":{"lang":"ES-ES","color":"var(--TC13)"}},{"insert":"\n","attributes":{"align":"justify","size":"normal"}}]},"rType":"richtext","paddV1":80,"hali":""}},"5-48WH-6-":{"type":"image","id":"5-48WH-6-","txtBg":{"fill":{"opac":1,"rgb":"var(--TC14)"}},"img":{"filt":{"opac":100,"gray":0,"blur":0,"tint":{"rgb":"#FFF","opac":0}},"pos":{"type":"crop","fit":{"bg":{"color":{"rgb":"#FFF","opac":100},"gradient":{"angle":0,"opac":0.5,"stops":[{"color":"#000000","pos":0},{"color":"#000000","pos":100}]}},"vali":"center","hali":"center"},"crop":{"bg":{"color":{"rgb":"#FFF","opac":0},"gradient":{"angle":0,"opac":0.5,"stops":[{"color":"#000000","pos":0},{"color":"#000000","pos":100}]}},"poi":{"orig":{"x":50,"y":50},"cust":{"x":50,"y":50}}},"mask":{"shape":1,"bg":{"color":{"rgb":"#FFF","opac":0},"gradient":{"angle":0,"opac":0.5,"stops":[{"color":"#000000","pos":0},{"color":"#000000","pos":100}]}}}}},"desc":{"val":{"ops":[{"insert":"c. Conclusiones y hallazgos","attributes":{"bold":true,"lang":"ES-ES","color":"var(--TC13)"}},{"insert":"\n","attributes":{"align":"center","size":"normal"}},{"insert":"\n","attributes":{"align":"justify","size":"normal"}},{"insert":"Resume las conclusiones clave de la investigación y destaca los hallazgos más importantes.","attributes":{"lang":"ES-ES","color":"var(--TC13)"}},{"insert":"\n","attributes":{"align":"justify","size":"normal"}}]},"rType":"richtext","paddV1":80,"hali":""}},"qNhYMSzAo":{"type":"image","id":"qNhYMSzAo","txtBg":{"fill":{"opac":1,"rgb":"var(--TC14)"}},"img":{"filt":{"opac":100,"gray":0,"blur":0,"tint":{"rgb":"#FFF","opac":0}},"pos":{"type":"crop","fit":{"bg":{"color":{"rgb":"#FFF","opac":100},"gradient":{"angle":0,"opac":0.5,"stops":[{"color":"#000000","pos":0},{"color":"#000000","pos":100}]}},"vali":"center","hali":"center"},"crop":{"bg":{"color":{"rgb":"#FFF","opac":0},"gradient":{"angle":0,"opac":0.5,"stops":[{"color":"#000000","pos":0},{"color":"#000000","pos":100}]}},"poi":{"orig":{"x":50,"y":50},"cust":{"x":50,"y":50}}},"mask":{"shape":1,"bg":{"color":{"rgb":"#FFF","opac":0},"gradient":{"angle":0,"opac":0.5,"stops":[{"color":"#000000","pos":0},{"color":"#000000","pos":100}]}}}}},"desc":{"val":{"ops":[{"insert":"d. Implicaciones y aplicaciones prácticas","attributes":{"bold":true,"color":"var(--TC13)","lang":"ES-ES"}},{"insert":"\n","attributes":{"align":"center","size":"normal"}},{"insert":"\n","attributes":{"size":"normal"}},{"insert":"Discute cómo los resultados pueden aplicarse en el mundo real y las implicaciones de la investigación.","attributes":{"color":"var(--TC13)","lang":"ES-ES"}},{"insert":"\n","attributes":{"align":"justify","size":"normal"}}]},"rType":"richtext","paddV1":80,"hali":""}}},"p":["RgjyAS79i","Ur2T_-mJj","5-48WH-6-","qNhYMSzAo"]}}}},"v":"1"}